tsoncli/__init__.py
tsoncli/msg.py
tsoncli-0.3.data/scripts/tson-cli
tsoncli-0.3.dist-info/LICENSE
tsoncli-0.3.dist-info/METADATA
tsoncli-0.3.dist-info/WHEEL
tsoncli-0.3.dist-info/top_level.txt
tsoncli-0.3.dist-info/RECORD
